MinecraftWikiSearch.py
MinecraftWikiSearch/DataReturn.py
MinecraftWikiSearch/Errors.py
MinecraftWikiSearch/JSONRead.py
MinecraftWikiSearch/MinecraftWikiSearch.py
MinecraftWikiSearch/Special_Entry.py
MinecraftWikiSearch/WebVisit.py
MinecraftWikiSearch/__init__.py
MinecraftWikiSearch/MwsFunctions/DataReturn.py
MinecraftWikiSearch/MwsFunctions/Special_Entry.py
MinecraftWikiSearch/MwsFunctions/WebVisit.py
MinecraftWikiSearch/MwsFunctions/__init__.py
MwsFunctions/DataReturn.py
MwsFunctions/Special_Entry.py
MwsFunctions/WebVisit.py
MwsFunctions/__init__.py
function/DataReturn.py
function/Special_Entry.py
function/WebVisit.py
function/__init__.py
MinecraftWikiSearch-1.1.6.dist-info/LICENSE
MinecraftWikiSearch-1.1.6.dist-info/METADATA
MinecraftWikiSearch-1.1.6.dist-info/WHEEL
MinecraftWikiSearch-1.1.6.dist-info/entry_points.txt
MinecraftWikiSearch-1.1.6.dist-info/top_level.txt
MinecraftWikiSearch-1.1.6.dist-info/RECORD
