Metadata-Version: 2.1
Name: MinecraftWikiSearch
Version: 1.1.6
Summary: 供机器人或者其他程序使用Minecraft Wiki查询的接口
Home-page: UNKNOWN
Author: MingxuanGame
Author-email: mingxuangame@outlook.com
License: Apache-2.0
Platform: UNKNOWN
